mimeo/__init__.py
mimeo/__main__.py
mimeo/exceptions.py
mimeo/mimeo.py
mimeo/config/__init__.py
mimeo/config/mimeo_config.py
mimeo/consumers/__init__.py
mimeo/consumers/consumer.py
mimeo/consumers/consumer_factory.py
mimeo/consumers/file_consumer.py
mimeo/consumers/http_consumer.py
mimeo/consumers/raw_consumer.py
mimeo/database/__init__.py
mimeo/database/cities.py
mimeo/database/countries.py
mimeo/database/exc.py
mimeo/database/mimeo_db.py
mimeo/generators/__init__.py
mimeo/generators/exc.py
mimeo/generators/generator.py
mimeo/generators/generator_factory.py
mimeo/generators/generator_utils.py
mimeo/generators/xml_generator.py
mimeo/logging/filters.py
mimeo/resources/__init__.py
mimeo/resources/cities.csv
mimeo/resources/countries.csv
mimeograph-2.6.0.dist-info/LICENSE
mimeograph-2.6.0.dist-info/METADATA
mimeograph-2.6.0.dist-info/WHEEL
mimeograph-2.6.0.dist-info/entry_points.txt
mimeograph-2.6.0.dist-info/top_level.txt
mimeograph-2.6.0.dist-info/RECORD
